[
    {
        "day": 1,
        "week_code": 1,
        "time": "9:00 Нечетная",
        "discipline": "пр ЭК ПО ФК И СПОРТУ",
        "classroom": null,
        "lecturer": null
    },
    {
        "day": 1,
        "week_code": 2,
        "time": "9:00 Четная",
        "discipline": "пр ЭК ПО ФК И СПОРТУ",
        "classroom": null,
        "lecturer": null
    },
    {
        "day": 1,
        "week_code": 1,
        "time": "10:50 Нечетная",
        "discipline": "лек ВЫСШ. МАТЕМАТ",
        "classroom": "443; ",
        "lecturer": "Щеглова А.В."
    },
    {
        "day": 1,
        "week_code": 2,
        "time": "10:50 Четная",
        "discipline": "лек ВЫСШ. МАТЕМАТ",
        "classroom": "443; ",
        "lecturer": "Щеглова А.В."
    },
    {
        "day": 1,
        "week_code": 1,
        "time": "12:40 Нечетная",
        "discipline": "пр ВЫСШ. МАТЕМАТ",
        "classroom": "214*; ",
        "lecturer": "Волченкова Н.М."
    },
    {
        "day": 1,
        "week_code": 2,
        "time": "12:40 Четная",
        "discipline": "пр ВЫСШ. МАТЕМАТ",
        "classroom": "214*; ",
        "lecturer": "Волченкова Н.М."
    },
    {
        "day": 2,
        "week_code": 2,
        "time": "9:00 Четная",
        "discipline": "пр ФИЗИКА",
        "classroom": "434*; ",
        "lecturer": "Кулинкин А.Б."
    },
    {
        "day": 2,
        "week_code": 2,
        "time": "10:50 Четная",
        "discipline": "лаб ФИЗИКА",
        "classroom": "323*; ",
        "lecturer": null
    },
    {
        "day": 2,
        "week_code": 1,
        "time": "12:40 Нечетная",
        "discipline": "лек ОСН РОС ГОС",
        "classroom": "443; ",
        "lecturer": "Лысенко Е.М."
    },
    {
        "day": 2,
        "week_code": 2,
        "time": "12:40 Четная",
        "discipline": "пр ПСИХ-Я.ПРОФ.ДЕЯ-НИ",
        "classroom": "425*; ",
        "lecturer": "Зареева Т.В."
    },
    {
        "day": 2,
        "week_code": 1,
        "time": "14:55 Нечетная",
        "discipline": "лек ФИЗИКА",
        "classroom": "327*; ",
        "lecturer": "Князева Т.Н."
    },
    {
        "day": 2,
        "week_code": 2,
        "time": "14:55 Четная",
        "discipline": "лек ФИЗИКА",
        "classroom": "327*; ",
        "lecturer": "Князева Т.Н."
    },
    {
        "day": 3,
        "week_code": 1,
        "time": "9:00 Нечетная",
        "discipline": "пр ЭК ПО ФК И СПОРТУ",
        "classroom": null,
        "lecturer": null
    },
    {
        "day": 3,
        "week_code": 2,
        "time": "9:00 Четная",
        "discipline": "пр ЭК ПО ФК И СПОРТУ",
        "classroom": null,
        "lecturer": null
    },
    {
        "day": 3,
        "week_code": 1,
        "time": "10:50 Нечетная",
        "discipline": "пр ИНФ.ТЕХН. И ПРОГР.",
        "classroom": "ВЦ 371; ",
        "lecturer": "Иванов В.Е."
    },
    {
        "day": 3,
        "week_code": 2,
        "time": "10:50 Четная",
        "discipline": "пр ИНФ.ТЕХН. И ПРОГР.",
        "classroom": "ВЦ 371; ",
        "lecturer": "Иванов В.Е."
    },
    {
        "day": 3,
        "week_code": 1,
        "time": "12:40 Нечетная",
        "discipline": "лек ИСТОРИЯ",
        "classroom": "443; ",
        "lecturer": "Савинов М.А."
    },
    {
        "day": 3,
        "week_code": 2,
        "time": "12:40 Четная",
        "discipline": "лек ИСТОРИЯ",
        "classroom": "493; ",
        "lecturer": "Савинов М.А."
    },
    {
        "day": 3,
        "week_code": 1,
        "time": "14:55 Нечетная",
        "discipline": "лек ИНФ.ТЕХН. И ПРОГР.",
        "classroom": "374; ",
        "lecturer": "Ракова И.К."
    },
    {
        "day": 3,
        "week_code": 2,
        "time": "14:55 Четная",
        "discipline": "лек ИНФ.ТЕХН. И ПРОГР.",
        "classroom": "374; ",
        "lecturer": "Ракова И.К."
    },
    {
        "day": 4,
        "week_code": 1,
        "time": "9:00 Нечетная",
        "discipline": "лек ПСИХ-Я.ПРОФ.ДЕЯ-НИ",
        "classroom": "437*; ",
        "lecturer": "Фомина А.П."
    },
    {
        "day": 4,
        "week_code": 2,
        "time": "9:00 Четная",
        "discipline": "лек ПСИХ-Я.ПРОФ.ДЕЯ-НИ",
        "classroom": "437*; ",
        "lecturer": "Фомина А.П."
    },
    {
        "day": 4,
        "week_code": 1,
        "time": "10:50 Нечетная",
        "discipline": "пр ИН. ЯЗ.",
        "classroom": "310*; ",
        "lecturer": "Паньшина А.И."
    },
    {
        "day": 4,
        "week_code": 2,
        "time": "10:50 Четная",
        "discipline": "пр ИН. ЯЗ.",
        "classroom": "310*; ",
        "lecturer": "Паньшина А.И."
    },
    {
        "day": 4,
        "week_code": 1,
        "time": "12:40 Нечетная",
        "discipline": "пр ИСТОРИЯ",
        "classroom": "507*а; ",
        "lecturer": "Савинов М.А."
    },
    {
        "day": 4,
        "week_code": 2,
        "time": "12:40 Четная",
        "discipline": "лек ХИМИЯ",
        "classroom": "433*; ",
        "lecturer": "Маслобоев Д.С."
    },
    {
        "day": 5,
        "week_code": 1,
        "time": "9:00 Нечетная",
        "discipline": "пр ИНЖ.И КОМП. ГРАФ",
        "classroom": "502*; ",
        "lecturer": "Глазунов К.О."
    },
    {
        "day": 5,
        "week_code": 2,
        "time": "9:00 Четная",
        "discipline": "пр ИНЖ.И КОМП. ГРАФ",
        "classroom": "502*; ",
        "lecturer": "Глазунов К.О."
    },
    {
        "day": 5,
        "week_code": 1,
        "time": "10:50 Нечетная",
        "discipline": "лаб ХИМИЯ",
        "classroom": "559*; ",
        "lecturer": "Лебедев В.Н."
    },
    {
        "day": 5,
        "week_code": 2,
        "time": "10:50 Четная",
        "discipline": "лаб ХИМИЯ",
        "classroom": "559*; ",
        "lecturer": "Лебедев В.Н."
    },
    {
        "day": 5,
        "week_code": 1,
        "time": "12:40 Нечетная",
        "discipline": "пр ОСН РОС ГОС",
        "classroom": "430*; ",
        "lecturer": "Клюев А.А."
    },
    {
        "day": 5,
        "week_code": 2,
        "time": "12:40 Четная",
        "discipline": "пр ОСН РОС ГОС",
        "classroom": "422*; ",
        "lecturer": "Клюев А.А."
    }
]