{
    "Number": "KPR02",
    "IdGroup": "2877",
    "Days": {
        "Day": {
            "Title": "Понедельник",
            "GroupLessons": {
                "Lesson": {
                    "DayTitle": {
                        "DayTitle": "Понедельник"
                    },
                    "WeekCode": {
                        "WeekCode": "1"
                    },
                    "Time": {
                        "Time": "9:00 Нечетная"
                    },
                    "Discipline": {
                        "Discipline": "лек ПО МИРТС"
                    },
                    "Lecturers": {
                        "Lecturer": {
                            "IdLecturer": {
                                "IdLecturer": "1507"
                            },
                            "ShortName": {
                                "ShortName": "Чернусь П.П."
                            }
                        }
                    },
                    "Classroom": {
                        "Classroom": "411*; "
                    }
                },
                "Lesson": {
                    "DayTitle": {
                        "DayTitle": "Понедельник"
                    },
                    "WeekCode": {
                        "WeekCode": "2"
                    },
                    "Time": {
                        "Time": "9:00 Четная"
                    },
                    "Discipline": {
                        "Discipline": "лек ПО МИРТС"
                    },
                    "Lecturers": {
                        "Lecturer": {
                            "IdLecturer": {
                                "IdLecturer": "1507"
                            },
                            "ShortName": {
                                "ShortName": "Чернусь П.П."
                            }
                        }
                    },
                    "Classroom": {
                        "Classroom": "411*; "
                    }
                },
                "Lesson": {
                    "DayTitle": {
                        "DayTitle": "Понедельник"
                    },
                    "WeekCode": {
                        "WeekCode": "1"
                    },
                    "Time": {
                        "Time": "10:50 Нечетная"
                    },
                    "Discipline": {
                        "Discipline": "пр ПО МИРТС"
                    },
                    "Lecturers": {
                        "Lecturer": {
                            "IdLecturer": {
                                "IdLecturer": "1507"
                            },
                            "ShortName": {
                                "ShortName": "Чернусь П.П."
                            }
                        }
                    },
                    "Classroom": {
                        "Classroom": "411*; "
                    }
                },
                "Lesson": {
                    "DayTitle": {
                        "DayTitle": "Понедельник"
                    },
                    "WeekCode": {
                        "WeekCode": "2"
                    },
                    "Time": {
                        "Time": "10:50 Четная"
                    },
                    "Discipline": {
                        "Discipline": "пр ПО МИРТС"
                    },
                    "Lecturers": {
                        "Lecturer": {
                            "IdLecturer": {
                                "IdLecturer": "1507"
                            },
                            "ShortName": {
                                "ShortName": "Чернусь П.П."
                            }
                        }
                    },
                    "Classroom": {
                        "Classroom": "411*; "
                    }
                },
                "Lesson": {
                    "DayTitle": {
                        "DayTitle": "Понедельник"
                    },
                    "WeekCode": {
                        "WeekCode": "1"
                    },
                    "Time": {
                        "Time": "12:40 Нечетная"
                    },
                    "Discipline": {
                        "Discipline": "пр ПР.ГМ.И МАШ.ГИДР."
                    },
                    "Lecturers": {
                        "Lecturer": {
                            "IdLecturer": {
                                "IdLecturer": "1365"
                            },
                            "ShortName": {
                                "ShortName": "Воротынцев Б.Н."
                            }
                        }
                    },
                    "Classroom": {
                        "Classroom": "152*; "
                    }
                },
                "Lesson": {
                    "DayTitle": {
                        "DayTitle": "Понедельник"
                    },
                    "WeekCode": {
                        "WeekCode": "2"
                    },
                    "Time": {
                        "Time": "12:40 Четная"
                    },
                    "Discipline": {
                        "Discipline": "пр ПР.ГМ.И МАШ.ГИДР."
                    },
                    "Lecturers": {
                        "Lecturer": {
                            "IdLecturer": {
                                "IdLecturer": "1365"
                            },
                            "ShortName": {
                                "ShortName": "Воротынцев Б.Н."
                            }
                        }
                    },
                    "Classroom": {
                        "Classroom": "152*; "
                    }
                }
            }
        },
        "Day": {
            "Title": "Вторник",
            "GroupLessons": {
                "Lesson": {
                    "DayTitle": {
                        "DayTitle": "Вторник"
                    },
                    "WeekCode": {
                        "WeekCode": "2"
                    },
                    "Time": {
                        "Time": "9:00 Четная"
                    },
                    "Discipline": {
                        "Discipline": "лек ПРОЕКТИРОВ. МС"
                    },
                    "Lecturers": {
                        "Lecturer": {
                            "IdLecturer": {
                                "IdLecturer": "1507"
                            },
                            "ShortName": {
                                "ShortName": "Чернусь П.П."
                            }
                        }
                    },
                    "Classroom": {
                        "Classroom": "411*; "
                    }
                },
                "Lesson": {
                    "DayTitle": {
                        "DayTitle": "Вторник"
                    },
                    "WeekCode": {
                        "WeekCode": "1"
                    },
                    "Time": {
                        "Time": "10:50 Нечетная"
                    },
                    "Discipline": {
                        "Discipline": "лаб ПРОЕКТИРОВ. МС"
                    },
                    "Lecturers": {
                        "Lecturer": {
                            "IdLecturer": {
                                "IdLecturer": "1507"
                            },
                            "ShortName": {
                                "ShortName": "Чернусь П.П."
                            }
                        }
                    },
                    "Classroom": {
                        "Classroom": "411*; "
                    }
                },
                "Lesson": {
                    "DayTitle": {
                        "DayTitle": "Вторник"
                    },
                    "WeekCode": {
                        "WeekCode": "2"
                    },
                    "Time": {
                        "Time": "10:50 Четная"
                    },
                    "Discipline": {
                        "Discipline": "лаб ПРОЕКТИРОВ. МС"
                    },
                    "Lecturers": {
                        "Lecturer": {
                            "IdLecturer": {
                                "IdLecturer": "1507"
                            },
                            "ShortName": {
                                "ShortName": "Чернусь П.П."
                            }
                        }
                    },
                    "Classroom": {
                        "Classroom": "411*; "
                    }
                }
            }
        },
        "Day": {
            "Title": "Среда",
            "GroupLessons": {
                "Lesson": {
                    "DayTitle": {
                        "DayTitle": "Среда"
                    },
                    "WeekCode": {
                        "WeekCode": "1"
                    },
                    "Time": {
                        "Time": "10:50 Нечетная"
                    },
                    "Discipline": {
                        "Discipline": "лек ПР.ГМ.И МАШ.ГИДР."
                    },
                    "Lecturers": {
                        "Lecturer": {
                            "IdLecturer": {
                                "IdLecturer": "916"
                            },
                            "ShortName": {
                                "ShortName": "Стажков С.М."
                            }
                        }
                    },
                    "Classroom": {
                        "Classroom": "270*(фесто); "
                    }
                }
            }
        }
    }
}