[
    {
        "day": 1,
        "week_code": 1,
        "time": "18:30",
        "discipline": "пр ПРОГНОЗ. С-ЭК ПРОЦ.",
        "classroom": "404*; ",
        "lecturer": "Шиндина Ю.А."
    },
    {
        "day": 1,
        "week_code": 2,
        "time": "18:30",
        "discipline": "пр БЖД",
        "classroom": "484; ",
        "lecturer": "Храмов А.В."
    },
    {
        "day": 1,
        "week_code": 1,
        "time": "20:05",
        "discipline": "лек ПРОГНОЗ. С-ЭК ПРОЦ.",
        "classroom": "403*; ",
        "lecturer": "Шиндина Ю.А."
    },
    {
        "day": 1,
        "week_code": 2,
        "time": "20:05",
        "discipline": "лек ОСН.БУХ.УЧ. И АУДИТА",
        "classroom": "507*а; ",
        "lecturer": "Катаев С.Е."
    },
    {
        "day": 2,
        "week_code": 1,
        "time": "18:30",
        "discipline": "лек БЖД",
        "classroom": "484; ",
        "lecturer": "Васильев В.А."
    },
    {
        "day": 2,
        "week_code": 2,
        "time": "18:30",
        "discipline": "лек БЖД",
        "classroom": "484; ",
        "lecturer": "Васильев В.А."
    },
    {
        "day": 2,
        "week_code": 1,
        "time": "20:05",
        "discipline": "пр ОСН.БУХ.УЧ. И АУДИТА",
        "classroom": "432*; ",
        "lecturer": "Кислицына С.В."
    },
    {
        "day": 3,
        "week_code": 1,
        "time": "18:30",
        "discipline": "лек УЧ.И АН.(ФИН.УЧ.)",
        "classroom": "430*; ",
        "lecturer": "Гавриленко И.В."
    },
    {
        "day": 3,
        "week_code": 1,
        "time": "20:05",
        "discipline": "пр УЧ.И АН.(ФИН.УЧ.)",
        "classroom": "530*; ",
        "lecturer": "Гавриленко И.В."
    },
    {
        "day": 4,
        "week_code": 1,
        "time": "18:30",
        "discipline": "лек СОЦ. ЭКОН. СТАТ.",
        "classroom": "425*; ",
        "lecturer": "Шишкин А.А."
    },
    {
        "day": 4,
        "week_code": 2,
        "time": "18:30",
        "discipline": "лек ОСНОВЫ ЦИФР.ЭК",
        "classroom": "425*; ",
        "lecturer": "Ревис В.Е."
    },
    {
        "day": 4,
        "week_code": 1,
        "time": "20:05",
        "discipline": "пр СОЦ. ЭКОН. СТАТ.",
        "classroom": "425*; ",
        "lecturer": "Шишкин А.А."
    },
    {
        "day": 4,
        "week_code": 2,
        "time": "20:05",
        "discipline": "пр ОСНОВЫ ЦИФР.ЭК",
        "classroom": "530*; ",
        "lecturer": "Ревис В.Е."
    },
    {
        "day": 5,
        "week_code": 2,
        "time": "18:30",
        "discipline": "лаб БЖД",
        "classroom": "384б; ",
        "lecturer": "Васильев В.А."
    },
    {
        "day": 5,
        "week_code": 2,
        "time": "20:05",
        "discipline": "лек ПРОГНОЗ. С-ЭК ПРОЦ.",
        "classroom": "507*а; ",
        "lecturer": "Шиндина Ю.А."
    }
]